{
  "routes": [
    {
      "method": "GET",
      "path": "/businesses",
      "handler": "business.find",
      "config": {
        "policies": []
      }
    },
    {
      "method": "GET",
      "path": "/businesses/count",
      "handler": "business.count",
      "config": {
        "policies": []
      }
    },
    {
      "method": "GET",
      "path": "/businesses/:id",
      "handler": "business.findOne",
      "config": {
        "policies": []
      }
    },
    {
      "method": "POST",
      "path": "/businesses",
      "handler": "business.create",
      "config": {
        "policies": []
      }
    },
    {
      "method": "PUT",
      "path": "/businesses/:id",
      "handler": "business.update",
      "config": {
        "policies": []
      }
    },
    {
      "method": "DELETE",
      "path": "/businesses/:id",
      "handler": "business.delete",
      "config": {
        "policies": []
      }
    }
  ]
}
